[{"id":"1","text":"\u6355\u98ce\u8ffd\u5f71","link":"page1.html","order":1},{"id":"2","text":"\u5357\u4eac\u7167\u76f8\u9986","link":"page2.html","order":2},{"id":"3","text":"\u6b7b\u795e\u6765\u4e86 \u8840\u8109\u8bc5\u5492","link":"page3.html","order":3},{"id":"4","text":"\u4f8f\u7f57\u7eaa\u91cd\u751f","link":"page4.html","order":4},{"id":"5","text":"\u751f\u4e07\u7269","link":"page5.html","order":5},{"id":"6","text":"\u671d\u96ea\u6cc9","link":"page6.html","order":6},{"id":"7","text":"\u4e03\u5929","link":"page7.html","order":7},{"id":"8","text":"\u73af\u86cb\u8054\u76df2","link":"page8.html","order":8},{"id":"9","text":"\u51e1\u4eba\u4fee\u4ed9\u4f20","link":"page9.html","order":9},{"id":"10","text":"F1\u72c2\u98d9\u98de\u8f66","link":"page10.html","order":10},{"id":"11","text":"\u6ce1\u8299\u5c0f\u4e38\u5b50","link":"page11.html","order":11}]